{
  "id": "",
  "name": "",
  "font_family": "iconfont",
  "css_prefix_text": "icon-",
  "description": "",
  "glyphs": [
    {
      "icon_id": "890166",
      "name": "好物_线",
      "font_class": "combinedshape",
      "unicode": "e602",
      "unicode_decimal": 58882
    },
    {
      "icon_id": "1330733",
      "name": "更多",
      "font_class": "gengduo",
      "unicode": "e748",
      "unicode_decimal": 59208
    },
    {
      "icon_id": "1668861",
      "name": "目录",
      "font_class": "mulu",
      "unicode": "e69a",
      "unicode_decimal": 59034
    },
    {
      "icon_id": "1905500",
      "name": "位置",
      "font_class": "position",
      "unicode": "e6bd",
      "unicode_decimal": 59069
    },
    {
      "icon_id": "2383579",
      "name": "我的说说",
      "font_class": "zixun",
      "unicode": "e503",
      "unicode_decimal": 58627
    },
    {
      "icon_id": "3050493",
      "name": "爱心",
      "font_class": "love-b",
      "unicode": "e60c",
      "unicode_decimal": 58892
    },
    {
      "icon_id": "3258069",
      "name": "购物",
      "font_class": "shouye-",
      "unicode": "e616",
      "unicode_decimal": 58902
    },
    {
      "icon_id": "3286138",
      "name": "左箭头",
      "font_class": "mjiantou-copy",
      "unicode": "e605",
      "unicode_decimal": 58885
    },
    {
      "icon_id": "3562696",
      "name": "放大镜",
      "font_class": "fangdajing",
      "unicode": "e63b",
      "unicode_decimal": 58939
    },
    {
      "icon_id": "5580739",
      "name": "购物车空",
      "font_class": "cart",
      "unicode": "e504",
      "unicode_decimal": 58628
    },
    {
      "icon_id": "7352523",
      "name": "商场",
      "font_class": "store",
      "unicode": "e713",
      "unicode_decimal": 59155
    },
    {
      "icon_id": "8617617",
      "name": "返回顶部",
      "font_class": "fanhuidingbu",
      "unicode": "e677",
      "unicode_decimal": 58999
    },
    {
      "icon_id": "10617536",
      "name": "海外",
      "font_class": "haiwai",
      "unicode": "e609",
      "unicode_decimal": 58889
    },
    {
      "icon_id": "11252593",
      "name": "我 的",
      "font_class": "wode",
      "unicode": "e61d",
      "unicode_decimal": 58909
    },
    {
      "icon_id": "11328939",
      "name": "右箭头",
      "font_class": "arrow-right-copy-copy-copy",
      "unicode": "e50e",
      "unicode_decimal": 58638
    },
    {
      "icon_id": "11683689",
      "name": "首页",
      "font_class": "ziyuan",
      "unicode": "e60b",
      "unicode_decimal": 58891
    },
    {
      "icon_id": "11695119",
      "name": "返 回",
      "font_class": "fanhui",
      "unicode": "e672",
      "unicode_decimal": 58994
    },
    {
      "icon_id": "12765588",
      "name": "更新",
      "font_class": "gengxin",
      "unicode": "e694",
      "unicode_decimal": 59028
    }
  ]
}
